PirxcyPinger/__init__.py
BOT_TMK-6.0.0.dist-info/METADATA
BOT_TMK-6.0.0.dist-info/WHEEL
BOT_TMK-6.0.0.dist-info/top_level.txt
BOT_TMK-6.0.0.dist-info/RECORD
