Metadata-Version: 2.1
Name: BOT-TMK
Version: 6.0.0
Summary: Async Tool For Uploading URL's To PirxcyPinger
Home-page: https://pirxcypingerfinal.pirxcy1942.repl.co/
Author: Pirxcy
Classifier: Programming Language :: Python :: 3
Classifier: License :: OSI Approved :: MIT License
Classifier: Operating System :: OS Independent
Requires-Dist: aiohttp
